coret/__init__.py
coret/coret.py
coret-0.1.1.dist-info/licenses/LICENSE
evaluation/__init__.py
evaluation/concept_extraction.py
evaluation/concept_metrics.py
evaluation/config.py
evaluation/coret_evaluation.py
evaluation/data_loader.py
evaluation/dataset_cleaner.py
evaluation/extractors.py
evaluation/logging_config.py
evaluation/main_eval.py
evaluation/utils.py
other/__init__.py
other/check_corr_mat_calcualtion_options_time.py
other/plot_histogram.py
other/plot_images.py
other/ram_to_size_of_corr_mat_calculation.py
coret-0.1.1.dist-info/METADATA
coret-0.1.1.dist-info/WHEEL
coret-0.1.1.dist-info/top_level.txt
coret-0.1.1.dist-info/RECORD
