Metadata-Version: 2.4
Name: coret
Version: 0.1.1
Summary: Surrogate based Concept Retrieval for Large Datasets
Author-email: Onr <restin3@gmail.com>
License: MIT
Project-URL: Homepage, https://github.com/Onr/surrogate_concept_retrieval
Project-URL: Bug_Tracker, https://github.com/Onr/surrogate_concept_retrieval/issues
Project-URL: Documentation, https://onr.github.io/surrogate_concept_retrieval/
Keywords: concept-retrieval,interpretability,xai,computer-vision,machine-learning
Classifier: Development Status :: 3 - Alpha
Classifier: Intended Audience :: Science/Research
Classifier: License :: OSI Approved :: MIT License
Classifier: Operating System :: OS Independent
Classifier: Programming Language :: Python :: 3
Classifier: Programming Language :: Python :: 3.9
Classifier: Programming Language :: Python :: 3.10
Classifier: Programming Language :: Python :: 3.11
Classifier: Programming Language :: Python :: 3.12
Classifier: Topic :: Scientific/Engineering :: Artificial Intelligence
Requires-Python: <3.13,>=3.9
License-File: LICENSE
Requires-Dist: numpy<2
Requires-Dist: toml>=0.10.2
Requires-Dist: tqdm>=4.67.1
Requires-Dist: faiss-gpu-cu12[fix-cuda]<2,>=1.11.0
Requires-Dist: cupy-cuda12x>=13.4.1
Requires-Dist: scipy>=1.13.1
Requires-Dist: scikit-learn>=1.6.1
Provides-Extra: test
Requires-Dist: pytest>=7.0.0; extra == "test"
Requires-Dist: pytest-cov>=4.0.0; extra == "test"
Requires-Dist: pytest-mock>=3.10.0; extra == "test"
Provides-Extra: dev
Requires-Dist: pytest>=7.0.0; extra == "dev"
Requires-Dist: pytest-cov>=4.0.0; extra == "dev"
Requires-Dist: pytest-mock>=3.10.0; extra == "dev"
Requires-Dist: black>=23.0.0; extra == "dev"
Requires-Dist: isort>=5.12.0; extra == "dev"
Requires-Dist: flake8>=6.0.0; extra == "dev"
Requires-Dist: mypy>=1.0.0; extra == "dev"
Requires-Dist: pre-commit>=3.0.0; extra == "dev"
Requires-Dist: autoflake>=2.0.0; extra == "dev"
Requires-Dist: docformatter>=1.7.0; extra == "dev"
Requires-Dist: bandit>=1.7.0; extra == "dev"
Requires-Dist: sphinx>=7.0.0; extra == "dev"
Requires-Dist: sphinx_rtd_theme>=2.0.0; extra == "dev"
Requires-Dist: sphinx-autodoc-typehints>=2.0.0; extra == "dev"
Provides-Extra: docs
Requires-Dist: sphinx>=7.0.0; extra == "docs"
Requires-Dist: sphinx_rtd_theme>=2.0.0; extra == "docs"
Requires-Dist: sphinx-autodoc-typehints>=2.0.0; extra == "docs"
Dynamic: license-file
